[
  {
    "node": {
      "messageId": 2596753677,
      "creationTime": 1692500322730831,
      "text": "你好啊",
      "author": "human",
      "linkifiedText": "你好啊",
      "state": "complete",
      "contentType": "text_markdown",
      "attachmentTruncationState": "not_truncated",
      "vote": null,
      "suggestedReplies": [],
      "voteReason": null,
      "__isNode": "Message",
      "__typename": "Message",
      "id": "TWVzc2FnZToyNTk2NzUzNjc3",
      "sourceType": "chat_input",
      "attachments": [],
      "linkifiedTextLengthOnCancellation": null,
      "textLengthOnCancellation": null
    },
    "cursor": "2596753677",
    "id": "TWVzc2FnZUVkZ2U6MjU5Njc1MzY3NzoyNTk2NzUzNjc3"
  },
  {
    "node": {
      "messageId": 2596753794,
      "creationTime": 1692500323402885,
      "text": "你好！我很高兴能够与你交流。有什么我可以帮助你的吗？",
      "author": "chinchilla",
      "linkifiedText": "你好！我很高兴能够与你交流。有什么我可以帮助你的吗？",
      "state": "complete",
      "contentType": "text_markdown",
      "attachmentTruncationState": "not_truncated",
      "vote": null,
      "suggestedReplies": [],
      "voteReason": null,
      "__isNode": "Message",
      "__typename": "Message",
      "id": "TWVzc2FnZToyNTk2NzUzNzk0",
      "sourceType": "chat_input",
      "attachments": [],
      "linkifiedTextLengthOnCancellation": null,
      "textLengthOnCancellation": null
    },
    "cursor": "2596753794",
    "id": "TWVzc2FnZUVkZ2U6MjU5Njc1Mzc5NDoyNTk2NzUzNzk0"
  },
  {
    "node": {
      "messageId": 2597104379,
      "creationTime": 1692502160336902,
      "text": "你会讲故事吗",
      "author": "human",
      "linkifiedText": "你会讲故事吗",
      "state": "complete",
      "contentType": "text_markdown",
      "attachmentTruncationState": "not_truncated",
      "vote": null,
      "suggestedReplies": [],
      "voteReason": null,
      "__isNode": "Message",
      "__typename": "Message",
      "id": "TWVzc2FnZToyNTk3MTA0Mzc5",
      "sourceType": "chat_input",
      "attachments": [],
      "linkifiedTextLengthOnCancellation": null,
      "textLengthOnCancellation": null
    },
    "cursor": "2597104379",
    "id": "TWVzc2FnZUVkZ2U6MjU5NzEwNDM3OToyNTk3MTA0Mzc5"
  },
  {
    "node": {
      "messageId": 2597104383,
      "creationTime": 1692502160367501,
      "text": "当然，我非常喜欢讲故事！请告诉我你想听什么类型的故事，我会尽力满足你的要求。是想听神话故事、童话故事、冒险故事还是其他类型的故事呢？",
      "author": "chinchilla",
      "linkifiedText": "当然，我非常喜欢讲故事！请告诉我你想听什么类型的故事，我会尽力满足你的要求。是想听神话故事、童话故事、冒险故事还是其他类型的故事呢？",
      "state": "complete",
      "contentType": "text_markdown",
      "attachmentTruncationState": "not_truncated",
      "vote": null,
      "suggestedReplies": [],
      "voteReason": null,
      "__isNode": "Message",
      "__typename": "Message",
      "id": "TWVzc2FnZToyNTk3MTA0Mzgz",
      "sourceType": "chat_input",
      "attachments": [],
      "linkifiedTextLengthOnCancellation": null,
      "textLengthOnCancellation": null
    },
    "cursor": "2597104383",
    "id": "TWVzc2FnZUVkZ2U6MjU5NzEwNDM4MzoyNTk3MTA0Mzgz"
  },
  {
    "node": {
      "messageId": 2597175369,
      "creationTime": 1692502531554679,
      "text": "",
      "author": "chat_break",
      "linkifiedText": "",
      "state": "complete",
      "contentType": "text_markdown",
      "attachmentTruncationState": "not_truncated",
      "vote": null,
      "suggestedReplies": [],
      "voteReason": null,
      "__isNode": "Message",
      "__typename": "Message",
      "id": "TWVzc2FnZToyNTk3MTc1MzY5",
      "sourceType": "chat_input",
      "attachments": [],
      "linkifiedTextLengthOnCancellation": null,
      "textLengthOnCancellation": null
    },
    "cursor": "2597175369",
    "id": "TWVzc2FnZUVkZ2U6MjU5NzE3NTM2OToyNTk3MTc1MzY5"
  },
  {
    "node": {
      "messageId": 2598406231,
      "creationTime": 1692509069285099,
      "text": "ubuntu怎么修改hostname",
      "author": "human",
      "linkifiedText": "ubuntu怎么修改hostname",
      "state": "complete",
      "contentType": "text_markdown",
      "attachmentTruncationState": "not_truncated",
      "vote": null,
      "suggestedReplies": [],
      "voteReason": null,
      "__isNode": "Message",
      "__typename": "Message",
      "id": "TWVzc2FnZToyNTk4NDA2MjMx",
      "sourceType": "chat_input",
      "attachments": [],
      "linkifiedTextLengthOnCancellation": null,
      "textLengthOnCancellation": null
    },
    "cursor": "2598406231",
    "id": "TWVzc2FnZUVkZ2U6MjU5ODQwNjIzMToyNTk4NDA2MjMx"
  },
  {
    "node": {
      "messageId": 2598406250,
      "creationTime": 1692509069358594,
      "text": "要修改Ubuntu的主机名，您可以按照以下步骤进行操作：\n\n1. 打开终端，可以通过按下Ctrl+Alt+T组合键快速打开终端。\n\n1. 输入以下命令来编辑主机名配置文件：\n\n   ````\n   sudo nano /etc/hostname\n   ```\n\n1. 在打开的文件中，将当前的主机名替换为您想要的新主机名。\n\n1. 按下Ctrl+O保存文件，然后按下Ctrl+X退出编辑器。\n\n1. 接下来，您还需要编辑hosts文件。输入以下命令：\n\n   ````\n   sudo nano /etc/hosts\n   ```\n\n1. 在打开的文件中，找到包含旧主机名的行，并将其替换为新主机名。\n\n1. 按下Ctrl+O保存文件，然后按下Ctrl+X退出编辑器。\n\n1. 最后，为了使更改生效，您需要重新启动系统。输入以下命令：\n\n   ````\n   sudo reboot\n   ```\n\n系统将重新启动，并且您的Ubuntu主机名将被成功修改为新的名称。请确保在修改主机名时小心操作，并确保输入正确的新主机名。",
      "author": "chinchilla",
      "linkifiedText": "要修改Ubuntu的主机名，您可以按照以下步骤进行操作：\n\n1. 打开终端，可以通过按下Ctrl+Alt+T组合键快速打开终端。\n\n1. 输入以下命令来编辑主机名配置文件：\n\n   ````\n   sudo nano /etc/hostname\n   ```\n\n1. 在打开的文件中，将当前的主机名替换为您想要的新主机名。\n\n1. 按下Ctrl+O保存文件，然后按下Ctrl+X退出编辑器。\n\n1. 接下来，您还需要编辑hosts文件。输入以下命令：\n\n   ````\n   sudo nano /etc/hosts\n   ```\n\n1. 在打开的文件中，找到包含旧主机名的行，并将其替换为新主机名。\n\n1. 按下Ctrl+O保存文件，然后按下Ctrl+X退出编辑器。\n\n1. 最后，为了使更改生效，您需要重新启动系统。输入以下命令：\n\n   ````\n   sudo reboot\n   ```\n\n系统将重新启动，并且您的Ubuntu主机名将被成功修改为新的名称。请确保在修改主机名时小心操作，并确保输入正确的新主机名。",
      "state": "complete",
      "contentType": "text_markdown",
      "attachmentTruncationState": "not_truncated",
      "vote": null,
      "suggestedReplies": [],
      "voteReason": null,
      "__isNode": "Message",
      "__typename": "Message",
      "id": "TWVzc2FnZToyNTk4NDA2MjUw",
      "sourceType": "chat_input",
      "attachments": [],
      "linkifiedTextLengthOnCancellation": null,
      "textLengthOnCancellation": null
    },
    "cursor": "2598406250",
    "id": "TWVzc2FnZUVkZ2U6MjU5ODQwNjI1MDoyNTk4NDA2MjUw"
  },
  {
    "node": {
      "messageId": 2598568078,
      "creationTime": 1692509925378307,
      "text": "home/caddy",
      "author": "human",
      "linkifiedText": "home/caddy",
      "state": "complete",
      "contentType": "text_markdown",
      "attachmentTruncationState": "not_truncated",
      "vote": null,
      "suggestedReplies": [],
      "voteReason": null,
      "__isNode": "Message",
      "__typename": "Message",
      "id": "TWVzc2FnZToyNTk4NTY4MDc4",
      "sourceType": "chat_input",
      "attachments": [],
      "linkifiedTextLengthOnCancellation": null,
      "textLengthOnCancellation": null
    },
    "cursor": "2598568078",
    "id": "TWVzc2FnZUVkZ2U6MjU5ODU2ODA3ODoyNTk4NTY4MDc4"
  },
  {
    "node": {
      "messageId": 2598568083,
      "creationTime": 1692509925405469,
      "text": "/home/caddy 是一个文件路径，它指向名为 \"caddy\" 的用户的主目录。在Ubuntu中，每个用户都有一个主目录，通常位于 /home/username。假设 \"caddy\" 是一个有效的用户，您可以通过以下方式进入该用户的主目录：\n\n1. 打开终端。\n\n1. 输入以下命令以切换到 \"caddy\" 用户的主目录：\n\n   ````\n   cd /home/caddy\n   ```\n\n现在，您应该位于 \"/home/caddy\" 目录中，可以在其中执行各种操作，例如浏览、编辑或复制文件。请注意，如果 \"caddy\" 用户不存在或没有权限访问该目录，您可能会遇到错误。请确保输入正确的用户名并具有适当的权限。",
      "author": "chinchilla",
      "linkifiedText": "/home/caddy 是一个文件路径，它指向名为 \"caddy\" 的用户的主目录。在Ubuntu中，每个用户都有一个主目录，通常位于 /home/username。假设 \"caddy\" 是一个有效的用户，您可以通过以下方式进入该用户的主目录：\n\n1. 打开终端。\n\n1. 输入以下命令以切换到 \"caddy\" 用户的主目录：\n\n   ````\n   cd /home/caddy\n   ```\n\n现在，您应该位于 \"/home/caddy\" 目录中，可以在其中执行各种操作，例如浏览、编辑或复制文件。请注意，如果 \"caddy\" 用户不存在或没有权限访问该目录，您可能会遇到错误。请确保输入正确的用户名并具有适当的权限。",
      "state": "complete",
      "contentType": "text_markdown",
      "attachmentTruncationState": "not_truncated",
      "vote": null,
      "suggestedReplies": [],
      "voteReason": null,
      "__isNode": "Message",
      "__typename": "Message",
      "id": "TWVzc2FnZToyNTk4NTY4MDgz",
      "sourceType": "chat_input",
      "attachments": [],
      "linkifiedTextLengthOnCancellation": null,
      "textLengthOnCancellation": null
    },
    "cursor": "2598568083",
    "id": "TWVzc2FnZUVkZ2U6MjU5ODU2ODA4MzoyNTk4NTY4MDgz"
  },
  {
    "node": {
      "messageId": 2598569540,
      "creationTime": 1692509933150408,
      "text": "tls.cache.maintenance   stopped background certificate maintenance      {\"cache\": \"0xc000280f00\"}\nError: loading initial config: loading new config: http app module: start: finalizing automatic HTTPS: managing certificates for [api.eop.nikiss.top]: automate: manage [api.eop.nikiss.top]: api.eop.nikiss.top: caching certificate: open caddy/certificates/acme-v02.api.letsencrypt.org-directory/api.eop.nikiss.top/api.eop.nikiss.top.key: not a directory",
      "author": "human",
      "linkifiedText": "tls.cache.maintenance   stopped background certificate maintenance      {\"cache\": \"0xc000280f00\"}\nError: loading initial config: loading new config: http app module: start: finalizing automatic HTTPS: managing certificates for [api.eop.nikiss.top]: automate: manage [api.eop.nikiss.top]: api.eop.nikiss.top: caching certificate: open caddy/certificates/acme-v02.api.letsencrypt.org-directory/api.eop.nikiss.top/api.eop.nikiss.top.key: not a directory",
      "state": "complete",
      "contentType": "text_markdown",
      "attachmentTruncationState": "not_truncated",
      "vote": null,
      "suggestedReplies": [],
      "voteReason": null,
      "__isNode": "Message",
      "__typename": "Message",
      "id": "TWVzc2FnZToyNTk4NTY5NTQw",
      "sourceType": "chat_input",
      "attachments": [],
      "linkifiedTextLengthOnCancellation": null,
      "textLengthOnCancellation": null
    },
    "cursor": "2598569540",
    "id": "TWVzc2FnZUVkZ2U6MjU5ODU2OTU0MDoyNTk4NTY5NTQw"
  },
  {
    "node": {
      "messageId": 2598569547,
      "creationTime": 1692509933188047,
      "text": "这个错误提示表明在加载Caddy的配置时出现了问题。具体来说，它指出无法找到证书的目录。\n\n要解决这个问题，您可以按照以下步骤进行操作：\n\n1. 确保您的证书文件和密钥文件位于正确的目录中。根据错误消息，您的密钥文件路径应该是 `caddy/certificates/acme-v02.api.letsencrypt.org-directory/api.eop.nikiss.top/api.eop.nikiss.top.key`。请检查该路径是否正确，并确保文件存在。\n\n1. 如果文件路径正确，但是文件不是一个目录，那么您可能需要手动创建目录。使用以下命令创建所需的目录：\n\n   ````\n   sudo mkdir -p caddy/certificates/acme-v02.api.letsencrypt.org-directory/api.eop.nikiss.top\n   ```\n\n1. 确保您的证书和密钥文件具有正确的权限。使用以下命令更改文件的权限：\n\n   ````\n   sudo chmod 644 caddy/certificates/acme-v02.api.letsencrypt.org-directory/api.eop.nikiss.top/api.eop.nikiss.top.key\n   ```\n\n1. 重新启动Caddy服务，以便它能够加载新的配置：\n\n   ````\n   sudo systemctl restart caddy\n   ```\n\n以上步骤应该帮助您解决该错误并成功加载证书。如果问题仍然存在，请确保您的证书和密钥文件正确，并且Caddy有权限访问它们。",
      "author": "chinchilla",
      "linkifiedText": "这个错误提示表明在加载Caddy的配置时出现了问题。具体来说，它指出无法找到证书的目录。\n\n要解决这个问题，您可以按照以下步骤进行操作：\n\n1. 确保您的证书文件和密钥文件位于正确的目录中。根据错误消息，您的密钥文件路径应该是 `caddy/certificates/acme-v02.api.letsencrypt.org-directory/api.eop.nikiss.top/api.eop.nikiss.top.key`。请检查该路径是否正确，并确保文件存在。\n\n1. 如果文件路径正确，但是文件不是一个目录，那么您可能需要手动创建目录。使用以下命令创建所需的目录：\n\n   ````\n   sudo mkdir -p caddy/certificates/acme-v02.api.letsencrypt.org-directory/api.eop.nikiss.top\n   ```\n\n1. 确保您的证书和密钥文件具有正确的权限。使用以下命令更改文件的权限：\n\n   ````\n   sudo chmod 644 caddy/certificates/acme-v02.api.letsencrypt.org-directory/api.eop.nikiss.top/api.eop.nikiss.top.key\n   ```\n\n1. 重新启动Caddy服务，以便它能够加载新的配置：\n\n   ````\n   sudo systemctl restart caddy\n   ```\n\n以上步骤应该帮助您解决该错误并成功加载证书。如果问题仍然存在，请确保您的证书和密钥文件正确，并且Caddy有权限访问它们。",
      "state": "complete",
      "contentType": "text_markdown",
      "attachmentTruncationState": "not_truncated",
      "vote": null,
      "suggestedReplies": [],
      "voteReason": null,
      "__isNode": "Message",
      "__typename": "Message",
      "id": "TWVzc2FnZToyNTk4NTY5NTQ3",
      "sourceType": "chat_input",
      "attachments": [],
      "linkifiedTextLengthOnCancellation": null,
      "textLengthOnCancellation": null
    },
    "cursor": "2598569547",
    "id": "TWVzc2FnZUVkZ2U6MjU5ODU2OTU0NzoyNTk4NTY5NTQ3"
  },
  {
    "node": {
      "messageId": 2598592990,
      "creationTime": 1692510056435649,
      "text": "/etc/systemd/system/multi-user.target.wants/目录",
      "author": "human",
      "linkifiedText": "/etc/systemd/system/multi-user.target.wants/目录",
      "state": "complete",
      "contentType": "text_markdown",
      "attachmentTruncationState": "not_truncated",
      "vote": null,
      "suggestedReplies": [],
      "voteReason": null,
      "__isNode": "Message",
      "__typename": "Message",
      "id": "TWVzc2FnZToyNTk4NTkyOTkw",
      "sourceType": "chat_input",
      "attachments": [],
      "linkifiedTextLengthOnCancellation": null,
      "textLengthOnCancellation": null
    },
    "cursor": "2598592990",
    "id": "TWVzc2FnZUVkZ2U6MjU5ODU5Mjk5MDoyNTk4NTkyOTkw"
  },
  {
    "node": {
      "messageId": 2598592999,
      "creationTime": 1692510056464002,
      "text": "`/etc/systemd/system/multi-user.target.wants/` 是一个目录，它包含了在系统启动时要自动启动的服务的符号链接。Systemd 是 Linux 系统中的一个初始化系统和服务管理器，它负责启动和管理系统的各个服务。\n\n在该目录中，每个符号链接对应一个具体的服务单元文件，这些服务单元文件通常位于 `/lib/systemd/system/` 或 `/etc/systemd/system/` 目录中。这些符号链接的名称与服务单元文件的名称相同，它们的存在表示在 multi-user.target（多用户目标）启动级别下，要自动启动对应的服务。\n\n当您向 `/etc/systemd/system/` 目录中添加一个新的服务单元文件时，可以通过创建一个指向该服务单元文件的符号链接来使其在系统启动时自动启动。这可以通过使用 `systemctl` 命令来完成。\n\n例如，假设您的服务单元文件位于 `/etc/systemd/system/my-service.service`，您可以使用以下命令创建一个符号链接：\n\n```\nsudo ln -s /etc/systemd/system/my-service.service /etc/systemd/system/multi-user.target.wants/my-service.service\n```\n\n这样，在系统启动时，`my-service.service` 将会自动启动。\n\n请注意，对于 `/etc/systemd/system/` 目录中的服务单元文件和符号链接的更改，通常需要使用 `systemctl` 命令重新加载 systemd 配置，例如：\n\n```\nsudo systemctl daemon-reload\n```\n\n这样，systemd 将会重新加载配置并识别您的新服务单元。",
      "author": "chinchilla",
      "linkifiedText": "`/etc/systemd/system/multi-user.target.wants/` 是一个目录，它包含了在系统启动时要自动启动的服务的符号链接。Systemd 是 Linux 系统中的一个初始化系统和服务管理器，它负责启动和管理系统的各个服务。\n\n在该目录中，每个符号链接对应一个具体的服务单元文件，这些服务单元文件通常位于 `/lib/systemd/system/` 或 `/etc/systemd/system/` 目录中。这些符号链接的名称与服务单元文件的名称相同，它们的存在表示在 multi-user.target（多用户目标）启动级别下，要自动启动对应的服务。\n\n当您向 `/etc/systemd/system/` 目录中添加一个新的服务单元文件时，可以通过创建一个指向该服务单元文件的符号链接来使其在系统启动时自动启动。这可以通过使用 `systemctl` 命令来完成。\n\n例如，假设您的服务单元文件位于 `/etc/systemd/system/my-service.service`，您可以使用以下命令创建一个符号链接：\n\n```\nsudo ln -s /etc/systemd/system/my-service.service /etc/systemd/system/multi-user.target.wants/my-service.service\n```\n\n这样，在系统启动时，`my-service.service` 将会自动启动。\n\n请注意，对于 `/etc/systemd/system/` 目录中的服务单元文件和符号链接的更改，通常需要使用 `systemctl` 命令重新加载 systemd 配置，例如：\n\n```\nsudo systemctl daemon-reload\n```\n\n这样，systemd 将会重新加载配置并识别您的新服务单元。",
      "state": "complete",
      "contentType": "text_markdown",
      "attachmentTruncationState": "not_truncated",
      "vote": null,
      "suggestedReplies": [],
      "voteReason": null,
      "__isNode": "Message",
      "__typename": "Message",
      "id": "TWVzc2FnZToyNTk4NTkyOTk5",
      "sourceType": "chat_input",
      "attachments": [],
      "linkifiedTextLengthOnCancellation": null,
      "textLengthOnCancellation": null
    },
    "cursor": "2598592999",
    "id": "TWVzc2FnZUVkZ2U6MjU5ODU5Mjk5OToyNTk4NTkyOTk5"
  },
  {
    "node": {
      "messageId": 2598621359,
      "creationTime": 1692510207239943,
      "text": "[Unit]\nDescription=Caddy\n\n[Service]\nWorkingDirectory=/home/caddy\nExecStart=/opt/node-v14.19.1-linux-x64/bin/node app.js\nExecReload=/bin/kill -s QUIT \nExecStop=/bin/kill -s QUIT \nEnvironment=\"PATH=/usr/local/sbin:/usr/local/bin:/usr/sbin:/usr/bin:/sbin:/bin:/usr/games:/usr/local/games:/snap/bin\"\n\n[Install]\nWantedBy=multi-user.target",
      "author": "human",
      "linkifiedText": "[Unit]\nDescription=Caddy\n\n[Service]\nWorkingDirectory=/home/caddy\nExecStart=/opt/node-v14.19.1-linux-x64/bin/node app.js\nExecReload=/bin/kill -s QUIT \nExecStop=/bin/kill -s QUIT \nEnvironment=\"PATH=/usr/local/sbin:/usr/local/bin:/usr/sbin:/usr/bin:/sbin:/bin:/usr/games:/usr/local/games:/snap/bin\"\n\n[Install]\nWantedBy=multi-user.target",
      "state": "complete",
      "contentType": "text_markdown",
      "attachmentTruncationState": "not_truncated",
      "vote": null,
      "suggestedReplies": [],
      "voteReason": null,
      "__isNode": "Message",
      "__typename": "Message",
      "id": "TWVzc2FnZToyNTk4NjIxMzU5",
      "sourceType": "chat_input",
      "attachments": [],
      "linkifiedTextLengthOnCancellation": null,
      "textLengthOnCancellation": null
    },
    "cursor": "2598621359",
    "id": "TWVzc2FnZUVkZ2U6MjU5ODYyMTM1OToyNTk4NjIxMzU5"
  },
  {
    "node": {
      "messageId": 2598621367,
      "creationTime": 1692510207269739,
      "text": "这是一个示例的 systemd 服务单元文件，用于定义一个名为 \"Caddy\" 的服务。根据该文件的内容，服务将在 `/home/caddy` 目录中启动一个名为 `app.js` 的 Node.js 应用程序。\n\n让我们逐个解释每个部分的含义：\n\n```\n[Unit]\nDescription=Caddy\n```\n\n在 `[Unit]` 部分，您可以提供有关服务的描述性信息。在这个例子中，服务被描述为 \"Caddy\"。\n\n```\n[Service]\nWorkingDirectory=/home/caddy\nExecStart=/opt/node-v14.19.1-linux-x64/bin/node app.js\nExecReload=/bin/kill -s QUIT \nExecStop=/bin/kill -s QUIT \nEnvironment=\"PATH=/usr/local/sbin:/usr/local/bin:/usr/sbin:/usr/bin:/sbin:/bin:/usr/games:/usr/local/games:/snap/bin\"\n```\n\n在 `[Service]` 部分，您可以指定服务的工作目录、启动命令以及其他相关配置。\n\n- `WorkingDirectory` 指定了服务的工作目录，即 `/home/caddy`。\n- `ExecStart` 定义了启动服务时要执行的命令，即使用 `/opt/node-v14.19.1-linux-x64/bin/node` 命令来运行 `app.js`。\n- `ExecReload` 定义了在重新加载服务时要执行的命令，这里使用 `/bin/kill -s QUIT` 发送 `QUIT` 信号。\n- `ExecStop` 定义了停止服务时要执行的命令，同样使用 `/bin/kill -s QUIT` 发送 `QUIT` 信号。\n- `Environment` 定义了服务的环境变量。在这个例子中，设置了 `PATH` 环境变量的值。\n\n```\n[Install]\nWantedBy=multi-user.target\n```\n\n在 `[Install]` 部分，您可以指定服务应该在哪个目标上启动。在这个例子中，服务将在 `multi-user.target` 上启动。\n\n要使用该服务单元文件，您需要将其保存为 `/etc/systemd/system/caddy.service`（或其他适当的位置），然后使用以下命令重新加载 systemd 配置：\n\n```\nsudo systemctl daemon-reload\n```\n\n接下来，您可以使用以下命令来启动、停止、重新加载或查看服务的状态：\n\n```\nsudo systemctl start caddy\nsudo systemctl stop caddy\nsudo systemctl reload caddy\nsudo systemctl status caddy\n```\n\n请确保根据您的环境和需求进行适当的更改，并确保相关的执行路径和文件正确存在。",
      "author": "chinchilla",
      "linkifiedText": "这是一个示例的 systemd 服务单元文件，用于定义一个名为 \"Caddy\" 的服务。根据该文件的内容，服务将在 `/home/caddy` 目录中启动一个名为 `app.js` 的 Node.js 应用程序。\n\n让我们逐个解释每个部分的含义：\n\n```\n[Unit]\nDescription=Caddy\n```\n\n在 `[Unit]` 部分，您可以提供有关服务的描述性信息。在这个例子中，服务被描述为 \"Caddy\"。\n\n```\n[Service]\nWorkingDirectory=/home/caddy\nExecStart=/opt/node-v14.19.1-linux-x64/bin/node app.js\nExecReload=/bin/kill -s QUIT \nExecStop=/bin/kill -s QUIT \nEnvironment=\"PATH=/usr/local/sbin:/usr/local/bin:/usr/sbin:/usr/bin:/sbin:/bin:/usr/games:/usr/local/games:/snap/bin\"\n```\n\n在 `[Service]` 部分，您可以指定服务的工作目录、启动命令以及其他相关配置。\n\n- `WorkingDirectory` 指定了服务的工作目录，即 `/home/caddy`。\n- `ExecStart` 定义了启动服务时要执行的命令，即使用 `/opt/node-v14.19.1-linux-x64/bin/node` 命令来运行 `app.js`。\n- `ExecReload` 定义了在重新加载服务时要执行的命令，这里使用 `/bin/kill -s QUIT` 发送 `QUIT` 信号。\n- `ExecStop` 定义了停止服务时要执行的命令，同样使用 `/bin/kill -s QUIT` 发送 `QUIT` 信号。\n- `Environment` 定义了服务的环境变量。在这个例子中，设置了 `PATH` 环境变量的值。\n\n```\n[Install]\nWantedBy=multi-user.target\n```\n\n在 `[Install]` 部分，您可以指定服务应该在哪个目标上启动。在这个例子中，服务将在 `multi-user.target` 上启动。\n\n要使用该服务单元文件，您需要将其保存为 `/etc/systemd/system/caddy.service`（或其他适当的位置），然后使用以下命令重新加载 systemd 配置：\n\n```\nsudo systemctl daemon-reload\n```\n\n接下来，您可以使用以下命令来启动、停止、重新加载或查看服务的状态：\n\n```\nsudo systemctl start caddy\nsudo systemctl stop caddy\nsudo systemctl reload caddy\nsudo systemctl status caddy\n```\n\n请确保根据您的环境和需求进行适当的更改，并确保相关的执行路径和文件正确存在。",
      "state": "complete",
      "contentType": "text_markdown",
      "attachmentTruncationState": "not_truncated",
      "vote": null,
      "suggestedReplies": [],
      "voteReason": null,
      "__isNode": "Message",
      "__typename": "Message",
      "id": "TWVzc2FnZToyNTk4NjIxMzY3",
      "sourceType": "chat_input",
      "attachments": [],
      "linkifiedTextLengthOnCancellation": null,
      "textLengthOnCancellation": null
    },
    "cursor": "2598621367",
    "id": "TWVzc2FnZUVkZ2U6MjU5ODYyMTM2NzoyNTk4NjIxMzY3"
  },
  {
    "node": {
      "messageId": 2598629022,
      "creationTime": 1692510247920682,
      "text": "caddy run如何指定Caddyfile",
      "author": "human",
      "linkifiedText": "caddy run如何指定Caddyfile",
      "state": "complete",
      "contentType": "text_markdown",
      "attachmentTruncationState": "not_truncated",
      "vote": null,
      "suggestedReplies": [],
      "voteReason": null,
      "__isNode": "Message",
      "__typename": "Message",
      "id": "TWVzc2FnZToyNTk4NjI5MDIy",
      "sourceType": "chat_input",
      "attachments": [],
      "linkifiedTextLengthOnCancellation": null,
      "textLengthOnCancellation": null
    },
    "cursor": "2598629022",
    "id": "TWVzc2FnZUVkZ2U6MjU5ODYyOTAyMjoyNTk4NjI5MDIy"
  },
  {
    "node": {
      "authorNickname": "chinchilla",
      "text": "要在使用 `caddy run` 命令时指定Caddyfile，您可以使用 `-config` 或 `-conf` 标志来指定Caddyfile 的路径。以下是示例命令：\n\n```\ncaddy run -config /path/to/Caddyfile\n```\n\n或者：\n\n```\ncaddy run -conf /path/to/Caddyfile\n```\n\n在上述命令中，将 `/path/to/Caddyfile` 替换为您实际的 Caddyfile 路径。\n\n请注意，`caddy run` 命令是 Caddy v2 版本中的命令，用于直接启动 Caddy 服务器。如果您使用的是 Caddy v1 版本，您可能需要使用不同的命令和选项来指定 Caddyfile。请查阅相应版本的文档以获取准确的命令和选项信息。",
      "author": "chinchilla",
      "__typename": "Message",
      "id": "TWVzc2FnZToyNTk4NjI5MDMz"
    },
    "cursor": "2598629033",
    "id": "TWVzc2FnZUVkZ2U6MjU5ODYyOTAzMzoyNTk4NjI5MDMz"
  },
  {
    "node": {
      "authorNickname": "human",
      "text": "python中的@property装饰器",
      "author": "human",
      "__typename": "Message",
      "id": "TWVzc2FnZToyNjAwOTkyNjE3"
    },
    "cursor": "2600992617",
    "id": "TWVzc2FnZUVkZ2U6MjYwMDk5MjYxNzoyNjAwOTkyNjE3"
  },
  {
    "node": {
      "authorNickname": "chinchilla",
      "text": "在Python中，`@property` 是一个装饰器，用于定义类中的属性访问器方法。属性访问器方法允许您在访问类的属性时执行自定义的逻辑。\n\n当您在一个方法前面使用 `@property` 装饰器时，它将把该方法转换为一个只读属性。这意味着您可以像访问普通属性一样访问该方法，而无需调用它。\n\n以下是一个示例，展示了如何使用 `@property` 装饰器定义一个只读属性：\n\n```python\nclass Circle:\n    def __init__(self, radius):\n        self.radius = radius\n\n    @property\n    def area(self):\n        return 3.14 * self.radius**2\n\ncircle = Circle(5)\nprint(circle.area)  # 调用属性访问器方法，输出结果为 78.5\n```\n\n在上面的示例中，我们定义了一个 `Circle` 类，它具有一个 `radius` 属性和一个使用 `@property` 装饰器修饰的 `area` 方法。`area` 方法计算圆的面积，并将其作为只读属性提供。\n\n通过在 `area` 方法上使用 `@property` 装饰器，我们可以直接通过 `circle.area` 访问面积，而无需调用方法。\n\n请注意，`@property` 装饰器只定义了属性的读取行为，如果您需要定义属性的写入行为，可以使用 `@<property_name>.setter` 装饰器来定义一个对应的设置器方法。\n\n希望这个解释对您有帮助！",
      "author": "chinchilla",
      "__typename": "Message",
      "id": "TWVzc2FnZToyNjAwOTkyNjI3"
    },
    "cursor": "2600992627",
    "id": "TWVzc2FnZUVkZ2U6MjYwMDk5MjYyNzoyNjAwOTkyNjI3"
  },
  {
    "node": {
      "authorNickname": "human",
      "text": "聊天记录存数据库的话，怎么设计合适",
      "author": "human",
      "__typename": "Message",
      "id": "TWVzc2FnZToyNjAzMjg4MDUy"
    },
    "cursor": "2603288052",
    "id": "TWVzc2FnZUVkZ2U6MjYwMzI4ODA1MjoyNjAzMjg4MDUy"
  },
  {
    "node": {
      "authorNickname": "chinchilla",
      "text": "设计一个合适的数据库模式来存储聊天记录可以有多种方法，具体取决于您的需求和系统架构。以下是一些常见的数据库设计模式供参考：\n\n1. 单表模式：\n\n   - 创建一个包含所有聊天记录的单个表。\n   - 表中可以包含发送者、接收者、消息内容、时间戳等字段。\n   - 这种简单的设计适用于小规模应用，但可能在数据量增加时性能下降。\n\n1. 分表模式：\n\n   - 根据聊天室、用户或时间等因素，在数据库中创建多个表来存储不同的聊天记录。\n   - 例如，可以按照聊天室ID创建不同的表，每个表存储该聊天室的聊天记录。\n   - 这种设计可以提高查询性能，但管理和维护多个表可能会更加复杂。\n\n1. 分库模式：\n\n   - 将聊天记录分布在不同的数据库中，每个数据库可以存储不同的聊天室或用户的记录。\n   - 这种设计适用于大规模应用，可以水平扩展数据库以处理高并发和大量数据。\n   - 管理多个数据库可能需要更高的操作和维护成本。\n\n无论选择哪种设计模式，还有一些其他的考虑因素：\n\n- 索引和查询优化：为常用的查询条件创建合适的索引，以提高查询性能。\n- 数据备份和恢复：定期备份聊天记录以防止数据丢失，并确保可以进行恢复。\n- 数据安全和隐私：根据需要采取适当的措施来保护聊天记录的安全性和隐私性。\n- 数据存储的规模和可扩展性：考虑到聊天记录的增长，选择能够处理大量数据并具有良好可扩展性的数据库解决方案。\n\n综上所述，设计合适的数据库模式需要综合考虑应用的规模、性能需求、数据安全等方面的因素。根据需求和系统架构，选择适合的设计模式，并根据实际情况进行调整和优化。",
      "author": "chinchilla",
      "__typename": "Message",
      "id": "TWVzc2FnZToyNjAzMjg4MDg2"
    },
    "cursor": "2603288086",
    "id": "TWVzc2FnZUVkZ2U6MjYwMzI4ODA4NjoyNjAzMjg4MDg2"
  }
]